{"chunk_definitions":[{"row":13,"row_count":1,"visible":true,"expansion_state":0,"options":{"engine":"r","label":"Setup CRAN Library for importing Libraries & Packages"},"document_id":"476CBE10","chunk_id":"caagi6tckptbx","chunk_label":"Setup CRAN Library for importing Libraries & Packages"},{"row":29,"row_count":1,"visible":true,"expansion_state":0,"options":{"engine":"r","label":"Install & Import required libraries"},"document_id":"476CBE10","chunk_id":"chizzjvsojjw1","chunk_label":"Install & Import required libraries"}],"doc_write_time":1678217523}